git_rebase_helper/__init__.py
git_rebase_helper/cli.py
git_rebase_helper/conflict.py
git_rebase_helper/dry_run.py
git_rebase_helper/rebase.py
git_rebase_helper/utils.py
git_rebase_helper/visualize.py
tests/__init__.py
tests/test_rebase.py
git_rebase_helper-0.3.dist-info/METADATA
git_rebase_helper-0.3.dist-info/WHEEL
git_rebase_helper-0.3.dist-info/entry_points.txt
git_rebase_helper-0.3.dist-info/top_level.txt
git_rebase_helper-0.3.dist-info/RECORD
