Metadata-Version: 2.1
Name: git-rebase-helper
Version: 0.3
Summary: A command line tool to simplify Git rebasing tasks.
Project-URL: Repository, https://github.com/andoriyaprashant/git_rebase_helper
Requires-Dist: click
Requires-Dist: gitpython
Requires-Dist: graphviz
